README.md
setup.py
discord_user/__init__.py
discord_user/discord_user.py
discord_user.py.egg-info/PKG-INFO
discord_user.py.egg-info/SOURCES.txt
discord_user.py.egg-info/dependency_links.txt
discord_user.py.egg-info/requires.txt
discord_user.py.egg-info/top_level.txt