Metadata-Version: 2.1
Name: discord-user.py
Version: 1.0.0
Summary: A library to create Discord User bots.
Home-page: https://github.com/Zakovskiy/discord_user.py
Author: Zakovskiy
Author-email: gogrugu@gmail.com
License: MIT
Download-URL: https://github.com/Zakovskiy/discord_user.py/tarball/master
Keywords: discord,user,discord.py,discord_user.py,discord-bot,api,python,zakovskiy,official
Platform: UNKNOWN
